gym_gopherfx/__init__.py
gym_gopherfx/envs/__init__.py
gym_gopherfx/envs/gopherfx_env.py
gym_gopherfx/envs/gopherfxv0_env.py
gym_gopherfx/envs/gopherfxv1_env.py
gym_gopherfx/envs/data/__init__.py
gym_gopherfx/envs/data/potential.py
gym_gopherfx/envs/data/reader.py
gym_gopherfx/envs/data/split.py
gym_gopherfx-0.2.1.dist-info/DESCRIPTION.rst
gym_gopherfx-0.2.1.dist-info/METADATA
gym_gopherfx-0.2.1.dist-info/RECORD
gym_gopherfx-0.2.1.dist-info/WHEEL
gym_gopherfx-0.2.1.dist-info/metadata.json
gym_gopherfx-0.2.1.dist-info/top_level.txt
