Metadata-Version: 2.0
Name: gym-gopherfx
Version: 0.2.1
Summary: A gym environment for reinforcement training on forex historical data.
Home-page: https://github.com/sergiuionescu/gym-gopherfx
Author: Sergiu Ionescu
Author-email: sergiu.ionescu@gmail.com
License: UNKNOWN
Platform: UNKNOWN
Classifier: Programming Language :: Python :: 3
Classifier: Operating System :: OS Independent
Requires-Dist: gym
